README.txt
setup.py
.settings/org.eclipse.core.resources.prefs
docs/HISTORY.txt
mobile/__init__.py
mobile.heurestics.egg-info/PKG-INFO
mobile.heurestics.egg-info/SOURCES.txt
mobile.heurestics.egg-info/dependency_links.txt
mobile.heurestics.egg-info/entry_points.txt
mobile.heurestics.egg-info/namespace_packages.txt
mobile.heurestics.egg-info/not-zip-safe
mobile.heurestics.egg-info/requires.txt
mobile.heurestics.egg-info/top_level.txt
mobile/heurestics/__init__.py
mobile/heurestics/contenttype.py
mobile/heurestics/poi.py
mobile/heurestics/simple.py
mobile/heurestics/sniffed.py
mobile/heurestics/tests.py
mobile/heurestics/vcard.py
mobile/heurestics/video.py