Metadata-Version: 1.0
Name: mobile.heurestics
Version: 0.1
Summary: A collections of rules-of-thumbs for dealing with mobile phones in web systems
Home-page: http://mfabrik.com
Author: Mikko Ohtamaa
Author-email: research@mfabrik.com
License: GPL
Keywords: mobile video vcard sniffer map javascript phone
Platform: UNKNOWN
Classifier: Programming Language :: Python
